vhip/__init__.py
vhip/mlmodel/__init__.py
vhip/mlmodel/build.py
vhip/mlmodel/compute_ml_features.py
vhip/mlmodel/genomes_features.py
vhip/mlmodel/ml_input.csv
vhip/mlmodel/read_sequence.py
vhip/network/properties.py
vhip/predict_interactions.py
virushostinteractionpredictor-1.0.0.dist-info/LICENSE
virushostinteractionpredictor-1.0.0.dist-info/METADATA
virushostinteractionpredictor-1.0.0.dist-info/WHEEL
virushostinteractionpredictor-1.0.0.dist-info/RECORD
