Metadata-Version: 2.1
Name: virushostinteractionpredictor
Version: 1.0.0
Summary: 
License: MIT
Author: Eric Bastien
Author-email: gbastien@umich.edu
Requires-Python: >=3.9
Classifier: License :: OSI Approved :: MIT License
Classifier: Programming Language :: Python :: 3
Classifier: Programming Language :: Python :: 3.9
Classifier: Programming Language :: Python :: 3.10
Classifier: Programming Language :: Python :: 3.11
Classifier: Programming Language :: Python :: 3.12
Requires-Dist: biopython
Requires-Dist: numpy
Requires-Dist: pandas
Requires-Dist: scikit-learn
